django_menu/__init__.py
django_menu/base.py
django_menu/conf.py
django_menu/exceptions.py
django_menu/middleware.py
django_menu_gauteron-0.0.3.dist-info/LICENSE
django_menu_gauteron-0.0.3.dist-info/METADATA
django_menu_gauteron-0.0.3.dist-info/WHEEL
django_menu_gauteron-0.0.3.dist-info/top_level.txt
django_menu_gauteron-0.0.3.dist-info/RECORD
